craft_ai_sdk/__init__.py
craft_ai_sdk/constants.py
craft_ai_sdk/core/data_store.py
craft_ai_sdk/core/deployments.py
craft_ai_sdk/core/endpoints.py
craft_ai_sdk/core/environment_variables.py
craft_ai_sdk/core/pipeline_executions.py
craft_ai_sdk/core/pipeline_metrics.py
craft_ai_sdk/core/pipeline_templates.py
craft_ai_sdk/core/pipelines.py
craft_ai_sdk/core/resource_metrics.py
craft_ai_sdk/core/steps.py
craft_ai_sdk/core/users.py
craft_ai_sdk/core/vector_database.py
craft_ai_sdk/exceptions.py
craft_ai_sdk/io.py
craft_ai_sdk/py.typed
craft_ai_sdk/sdk.py
craft_ai_sdk/shared/authentication.py
craft_ai_sdk/shared/environments.py
craft_ai_sdk/shared/execution_context.py
craft_ai_sdk/shared/helpers.py
craft_ai_sdk/shared/logger.py
craft_ai_sdk/shared/request_response_handler.py
craft_ai_sdk/shared/types.py
craft_ai_sdk/shared/warnings.py
craft_ai_sdk/utils/__init__.py
craft_ai_sdk/utils/datetime_utils.py
craft_ai_sdk/utils/dict_utils.py
craft_ai_sdk/utils/file_utils.py
craft_ai_sdk-0.70.2.dist-info/METADATA
craft_ai_sdk-0.70.2.dist-info/WHEEL
craft_ai_sdk-0.70.2.dist-info/entry_points.txt
craft_ai_sdk-0.70.2.dist-info/licenses/LICENSE
craft_ai_sdk-0.70.2.dist-info/RECORD
