Metadata-Version: 2.4
Name: craft-ai-sdk
Version: 0.70.2
Summary: Craft AI MLOps platform SDK
License-Expression: Apache-2.0
License-File: LICENSE
Author: Craft AI
Author-email: contact@craft.ai
Requires-Python: >=3.10
Classifier: Programming Language :: Python :: 3
Classifier: Programming Language :: Python :: 3.10
Classifier: Programming Language :: Python :: 3.11
Classifier: Programming Language :: Python :: 3.12
Classifier: Programming Language :: Python :: 3.13
Classifier: Programming Language :: Python :: 3.14
Requires-Dist: StrEnum (>=0.4.9)
Requires-Dist: pyjwt (>=2.4.0)
Requires-Dist: requests (>=2.32.4)
Requires-Dist: weaviate-client (>=4.15.3)
